{"global_id": {"global_id": 1.0}, "local_id": {"local_id": 1.0}, "species_id": {"species_id": 1.0}, "species_name": {"species_name": 1.0}, "donor_age": {"donor_age": 1.0}, "donor_ethnicity": {"donor_ethnicity": 1.0}, "donor_health_status": {"donor_health_status": 1.0}, "donor_id": {"donor_id": 1.0}, "donor_sex": {"donor_sex": 1.0}, "biospecimen_class_term_id": {"biospecimen_class_term_id": 1.0}, "biospecimen_class_term_label": {"biospecimen_class_term_label": 1.0}, "sample_type_term_id": {"sample_type_term_id": 1.0}, "sample_type_term_label": {"sample_type_term_label": 1.0}, "sample_type_summary": {"sample_type_summary": 1.0}, "phenotype_term_id": {"phenotype_term_id": 1.0}, "phenotype_term_label": {"phenotype_term_label": 1.0}}